{
  "date": "2026-05-21",
  "sourceName": "Mailing List",
  "sourceType": "lkml",
  "generatedAt": "2026-05-21T00:05:56.325Z",
  "summary": "# 今日社区动态（MiniMax-M2.7 | 2026-05-20 ~ 2026-05-21）\n\n- 🧠 [Memory](#subsystem-Memory)：虚拟化内存分配效率提升（virtio balloon/hugetlb 跳过冗余清零），引入 RT 任务 GFP_ATOMIC_RT 支持和 DAMON per-fd 追踪能力，多项 bugfix 提升内存子系统稳定性\n- 🧭 [Scheduling](#subsystem-Scheduling)：sched_ext arena 内存管理和子分配器优化降低碎片化风险，isolcpus 配置提升实时 IO 调度确定性，sframe 硬件辅助栈展开改善性能追踪\n- 🌐 [Networking](#subsystem-Networking)：多驱动性能优化（RSS 多核负载均衡、PTP 时钟同步、IPsec 硬件卸载），修复多处竞态和安全问题，Bluetooth L2CAP 和 RDS 命名空间隔离增强协议安全性\n- 🛡 [Security](#subsystem-Security)：维护性更新\n- 📈 [Observability](#subsystem-Observability)：维护性更新\n- 🗂 [Filesystem & Storage](#subsystem-Filesystem%20%26%20Storage)：维护性更新\n- 🏗 [Architecture](#subsystem-Architecture)：s390/riscv 性能优化提升上下文切换和字符串操作，PCI 热插拔 uevent 属性、DMA 合并 API、KVM 预热内存等多项新功能完善系统能力\n- 🔋 [Power Management](#subsystem-Power%20Management)：维护性更新\n- ⏱ [Clocks & Timers](#subsystem-Clocks%20%26%20Timers)：维护性更新\n- ⚙ [Core Kernel](#subsystem-Core%20Kernel)：维护性更新\n- 🧩 [IO_uring](#subsystem-IO_uring)：维护性更新\n- 🧩 [Virtualization](#subsystem-Virtualization)：维护性更新\n- 🧰 [Drivers](#subsystem-Drivers)：GPU 性能调优接口（drm/msm PERFCNTR_CONFIG）、USB-HID 兼容性增强（CP2112）、GPIO API 演进和多项驱动修复\n\n## Memory\n- `perf` `feature` virtio balloon、hugetlb 等跳过冗余清零操作，减少不必要的内存初始化开销，在虚拟化场景下可显著提升内存分配效率 [↗](https://lkml.org/lkml/2026/5/20/2492)\n- `perf` `feature` 内存热插中优化 zone 连续性检查逻辑，降低计算复杂度并减少内存在线/离线操作的延迟 [↗](https://lkml.org/lkml/2026/5/20/796)\n- `perf` `feature` page_owner 添加 per-fd 过滤基础设施，使开发者能按文件描述符追踪内存分配，便于定位特定进程的内存泄漏问题 [↗](https://lkml.org/lkml/2026/5/20/1152)\n- `feature` 为 RT 任务引入 GFP_ATOMIC_RT 标志，解决实时进程在原子上下文中的内存分配问题，确保内核实时性需求得到正确支持 [↗](https://lkml.org/lkml/2026/5/20/2313)\n- `feature` nommu 系统实现足够的 vmap 支持以兼容压缩内存模块，扩展了嵌入式设备上的内存管理能力 [↗](https://lkml.org/lkml/2026/5/21/3)\n- `feature` DAMON/core 追踪初始化时的步长值，帮助分析内存访问模式的准确性并优化数据采集开销 [↗](https://lkml.org/lkml/2026/5/20/1747)\n- `feature` hugetlb 错误路径中恢复预留，解决 hugetlb_mfill 失败时预留未释放导致的内存泄漏问题 [↗](https://lkml.org/lkml/2026/5/20/63)\n- `bugfix` 修复 COW 故障处理时不恰当安装 PMD 映射的问题，避免不必要的页表展开和潜在的内存浪费 [↗](https://lkml.org/lkml/2026/5/20/1788)\n- `bugfix` page_alloc 修复不可回收内存的碎片整理模式设置，确保高阶分配失败时不会错误回退到内存压缩逻辑 [↗](https://lkml.org/lkml/2026/5/20/1251)\n- `bugfix` CMA 调试模块修复对非活跃 CMA 区域的无效访问，防止内核在内存热插拔测试场景下的崩溃 [↗](https://lkml.org/lkml/2026/5/20/303)\n- `bugfix` memory-failure 修复大页锁的 AA 死锁问题，消除 get_hwpoison_page 获取大页时的潜在竞争条件 [↗](https://lkml.org/lkml/2026/5/20/138)\n- `bugfix` slub 修复目录项注册过程中可能的竞态问题，提升文件系统元数据操作的稳定性 [↗](https://lkml.org/lkml/2026/5/20/89)\n\n## Scheduling\n- `perf` `feature` 调度器子系统通过多批sched_ext补丁完善arena内存管理和cid支持，其中子分配器优化了BPF arena内存使用效率，降低碎片化风险 [↗](https://lkml.org/lkml/2026/5/20/2670)\n- `perf` `feature` blk-mq层面新增isolcpus配置支持，使块设备IO路径能识别CPU隔离策略，提升实时性场景下IO调度的确定性和性能隔离效果 [↗](https://lkml.org/lkml/2026/5/20/2424)\n- `perf` `feature` 引入sframe格式栈展开支持，通过硬件辅助方式加速异常处理和调试场景的栈回溯，与调度器结合可改善延迟敏感操作的性能追踪 [↗](https://lkml.org/lkml/2026/5/20/1826)\n- `feature` sched_ext强制cid形式调度器必须使用arena，为大规模多租户调度场景提供更安全的内存隔离基础 [↗](https://lkml.org/lkml/2026/5/20/2663)\n- `feature` 将set_cmask操作迁移至arena驻留实现，使cpuset掩码管理更安全且支持动态扩容，为复杂调度策略提供更灵活的接口 [↗](https://lkml.org/lkml/2026/5/20/2664)\n- `bugfix` 修复RT任务fork时timer_slack_ns未正确继承的问题，确保实时任务的时间预算控制符合预期，避免延迟调整被意外覆盖 [↗](https://lkml.org/lkml/2026/5/20/1329)\n\n## Networking\n- `perf` `feature` fbnic 驱动新增 LED 支持，可实现网络接口状态指示，提升可观测性与管理便利性 [↗](https://lkml.org/lkml/2026/5/20/2567)\n- `perf` `feature` 9p 文件系统在构建工作负载场景下进行性能优化，通过优化元数据操作减少开销，对大型项目构建有显著收益 [↗](https://lkml.org/lkml/2026/5/20/2179)\n- `perf` `feature` DPLL 子系统新增通用 DPLL 类型支持并完成 Intel ice 驱动完整实现，为时钟同步提供标准化接口 [↗](https://lkml.org/lkml/2026/5/20/826)\n- `perf` `feature` CAN BCM 驱动将 rx_op 释放延迟至工作队列以修复竞态问题，提升驱动稳定性 [↗](https://lkml.org/lkml/2026/5/20/521)\n- `perf` `feature` r8169 驱动为 RTL8127 添加 RSS 接收端缩放支持，改善多核系统下网络吞吐量与负载均衡 [↗](https://lkml.org/lkml/2026/5/20/190)\n- `feature` AQC113 以太网卡驱动新增 PTP 时间同步支持，实现硬件级精确时钟功能 [↗](https://lkml.org/lkml/2026/5/20/1495)\n- `feature` BCMGENET 驱动在关闭时保持 RBUF EEE 与功耗管理禁用状态，避免退出时异常行为 [↗](https://lkml.org/lkml/2026/5/20/2438)\n- `feature` XFRM iptfs 在克隆安全关联时重置运行时状态，确保隧道状态正确传递 [↗](https://lkml.org/lkml/2026/5/21/12)\n- `feature` tg3 驱动添加 napi_disable 与 pci_disable_device 的保护检查，防止错误使用顺序导致系统崩溃 [↗](https://lkml.org/lkml/2026/5/20/2235)\n- `feature` TUN 设备在 XDP 帧被拒绝时正确释放内存页，修复潜在的内存泄漏问题 [↗](https://lkml.org/lkml/2026/5/20/1835)\n- `feature` octeontx2-af 在邮箱处理函数中验证 pcifunc 参数，提升接口安全性 [↗](https://lkml.org/lkml/2026/5/20/1883)\n- `feature` SFP 模块支持列表新增 OEM 2.5G 光模块兼容条目，解决特定硬件识别问题 [↗](https://lkml.org/lkml/2026/5/20/1792)\n- `feature` ieee802154 协议栈恢复遗留 LLSEC 导出功能并移除相关废弃代码 [↗](https://lkml.org/lkml/2026/5/20/1534)\n- `feature` Bluetooth L2CAP 层拒绝超出限制的 BR/EDR 信令包，增强协议安全性 [↗](https://lkml.org/lkml/2026/5/20/1416)\n- `feature` BPF sockmap 保持 sk_msg 副本状态同步，修复消息处理中的状态一致性问题 [↗](https://lkml.org/lkml/2026/5/20/957)\n- `feature` RDS 协议过滤 getsockopt 信息至调用者所在网络命名空间，增强命名空间隔离安全性 [↗](https://lkml.org/lkml/2026/5/20/631)\n- `feature` bonding 驱动支持 LAG 模式下的 IPsec 硬件卸载，扩展网卡Offload能力 [↗](https://lkml.org/lkml/2026/5/20/527)\n- `feature` octeontx2-af NPC 修复 LBK 通道的 allmulticast 跳过逻辑，提升数据包处理正确性 [↗](https://lkml.org/lkml/2026/5/20/234)\n- `feature` DSA yt921x 交换机驱动添加 ACL 访问控制列表支持，丰富交换功能 [↗](https://lkml.org/lkml/2026/5/20/137)\n- `feature` octeontx2-af NPC 引擎多项增强功能，改善规则解析与处理能力 [↗](https://lkml.org/lkml/2026/5/20/121)\n- `feature` vsock 保持 poll 关闭状态一致性，修复关闭流程中的状态同步问题 [↗](https://lkml.org/lkml/2026/5/20/12)\n- `bugfix` sunrpc 使用 kref_get_unless_zero 替代有缺陷的引用计数操作，避免潜在的空指针解引用 [↗](https://lkml.org/lkml/2026/5/20/2119)\n- `bugfix` alx 驱动修复可能的缓冲区溢出漏洞，提升安全性 [↗](https://lkml.org/lkml/2026/5/20/2072)\n- `bugfix` netlink 修复跨命名空间 nsid 报告问题，确保命名空间标识符正确传递 [↗](https://lkml.org/lkml/2026/5/20/2291)\n- `bugfix` L2TP PPPoL2TP 在操作前持有会话引用计数，防止会话在持有期间被释放 [↗](https://lkml.org/lkml/2026/5/20/1461)\n- `bugfix` TAP 设备修复 SIOCGIFHWADDR ioctl 中的栈信息泄漏问题 [↗](https://lkml.org/lkml/2026/5/20/499)\n- `bugfix` ESP 协议修复 skb_to_sgvec 调用中的页片段引用泄漏 [↗](https://lkml.org/lkml/2026/5/20/438)\n- `bugfix` qed 驱动修复 qed_cxt_tables_alloc 中的双重释放问题 [↗](https://lkml.org/lkml/2026/5/20/416)\n- `bugfix` MACsec 修复 XPN 低序号的抗重放保护在 PN 回绕时的计算错误 [↗](https://lkml.org/lkml/2026/5/20/217)\n- `bugfix` octeontx2-pf 在接口重启时保留 ethtool 统计数据，避免计数重置 [↗](https://lkml.org/lkml/2026/5/20/787)\n- `other` 其他改动多为小修正、清理或配置更新，整体风险较低，详情见：[↗](https://lkml.org/lkml/2026/5/20/1784) [↗](https://lkml.org/lkml/2026/5/20/1506) [↗](https://lkml.org/lkml/2026/5/20/932) [↗](https://lkml.org/lkml/2026/5/20/133)\n\n## Security\n- `other` 其他改动多为小修正、清理或配置更新，整体风险较低，详情见：[↗](https://lkml.org/lkml/2026/5/20/572)\n\n## Observability\n- `other` 其他改动多为小修正、清理或配置更新，整体风险较低，详情见：[↗](https://lkml.org/lkml/2026/5/20/1906) [↗](https://lkml.org/lkml/2026/5/20/1413) [↗](https://lkml.org/lkml/2026/5/20/2061) [↗](https://lkml.org/lkml/2026/5/20/1307) [↗](https://lkml.org/lkml/2026/5/20/943) [↗](https://lkml.org/lkml/2026/5/20/2662) [↗](https://lkml.org/lkml/2026/5/20/2661) [↗](https://lkml.org/lkml/2026/5/20/2548) [↗](https://lkml.org/lkml/2026/5/20/2423) [↗](https://lkml.org/lkml/2026/5/20/2151) [↗](https://lkml.org/lkml/2026/5/20/1759) [↗](https://lkml.org/lkml/2026/5/20/1240) [↗](https://lkml.org/lkml/2026/5/20/1032) [↗](https://lkml.org/lkml/2026/5/20/781) [↗](https://lkml.org/lkml/2026/5/20/102) [↗](https://lkml.org/lkml/2026/5/20/2394) [↗](https://lkml.org/lkml/2026/5/20/824) [↗](https://lkml.org/lkml/2026/5/20/164) [↗](https://lkml.org/lkml/2026/5/20/2448) [↗](https://lkml.org/lkml/2026/5/20/2444) [↗](https://lkml.org/lkml/2026/5/20/928) [↗](https://lkml.org/lkml/2026/5/20/66)\n\n## Filesystem & Storage\n- `other` 其他改动多为小修正、清理或配置更新，整体风险较低，详情见：[↗](https://lkml.org/lkml/2026/5/20/2296) [↗](https://lkml.org/lkml/2026/5/20/2600) [↗](https://lkml.org/lkml/2026/5/20/2546) [↗](https://lkml.org/lkml/2026/5/20/2553) [↗](https://lkml.org/lkml/2026/5/20/2081) [↗](https://lkml.org/lkml/2026/5/20/2257) [↗](https://lkml.org/lkml/2026/5/20/1334) [↗](https://lkml.org/lkml/2026/5/20/465) [↗](https://lkml.org/lkml/2026/5/20/394) [↗](https://lkml.org/lkml/2026/5/21/14) [↗](https://lkml.org/lkml/2026/5/20/1543) [↗](https://lkml.org/lkml/2026/5/20/1328) [↗](https://lkml.org/lkml/2026/5/20/1321) [↗](https://lkml.org/lkml/2026/5/20/1210) [↗](https://lkml.org/lkml/2026/5/20/858) [↗](https://lkml.org/lkml/2026/5/20/468) [↗](https://lkml.org/lkml/2026/5/20/862) [↗](https://lkml.org/lkml/2026/5/20/925) [↗](https://lkml.org/lkml/2026/5/20/456) [↗](https://lkml.org/lkml/2026/5/20/214) [↗](https://lkml.org/lkml/2026/5/20/1027) [↗](https://lkml.org/lkml/2026/5/20/996) [↗](https://lkml.org/lkml/2026/5/20/579) [↗](https://lkml.org/lkml/2026/5/20/216) [↗](https://lkml.org/lkml/2026/5/20/193) [↗](https://lkml.org/lkml/2026/5/20/139)\n\n## Architecture\n- `perf` `feature` s390: 引入改进的 this_cpu 操作，通过优化 percpu 访问路径提升上下文切换和中断处理性能 [↗](https://lkml.org/lkml/2026/5/20/761)\n- `perf` `feature` KVM/s390: 为原子中断注入引入 kvm_arch_set_irq_inatomic 接口，解决高并发场景下 vCPU 中断注入的竞争问题 [↗](https://lkml.org/lkml/2026/5/20/1942)\n- `perf` `feature` riscv: 为 riscv 添加优化的 memchr 实现，通过汇编指令直接搜索字节以加速字符串操作性能 [↗](https://lkml.org/lkml/2026/5/20/1921)\n- `perf` `feature` riscv: 为 riscv 添加优化的 memcmp 实现，利用向量指令加速内存比较并扩展 KUnit 测试覆盖 [↗](https://lkml.org/lkml/2026/5/20/1278)\n- `perf` `feature` arm64/dts/renesas: 为 SDHI 节点添加 max-frequency 属性以优化时钟频率设置，可提升 SD 卡读写吞吐 [↗](https://lkml.org/lkml/2026/5/20/1150)\n- `perf` `feature` usb/dwc2: 移除 dwc2_hcd_save_data_toggle 中的冗余 WARN 检查，消除不必要的性能开销和日志噪音 [↗](https://lkml.org/lkml/2026/5/20/1470)\n- `feature` bpf: 实现 arena 内核错误的 scratch page 恢复机制，增强 BPF 内存管理可靠性 [↗](https://lkml.org/lkml/2026/5/20/2660)\n- `feature` PCI/hotplug: 添加 'uevent' sysfs 属性以支持用户空间触发热插拔事件，增强设备管理灵活性 [↗](https://lkml.org/lkml/2026/5/20/2642)\n- `feature` dmaengine: 引入配置与传输合并的新 API，允许应用程序在单次调用中同时指定传输配置与启动信号 [↗](https://lkml.org/lkml/2026/5/20/2530)\n- `feature` PCI/ats: 支持某些 ATS 设备始终保持 ATS 开启状态，消除频繁开关带来的延迟开销 [↗](https://lkml.org/lkml/2026/5/20/2242)\n- `feature` PCI/mediatek: 添加 EcoNet EN7528 及 EN751221 芯片的 PCIe 控制器支持，扩展驱动硬件覆盖范围 [↗](https://lkml.org/lkml/2026/5/20/2140)\n- `feature` vfio/pci/s390x: 为 s390x 架构的 vfio-pci 设备实现错误恢复机制，增强虚拟机可靠性 [↗](https://lkml.org/lkml/2026/5/20/1997)\n- `feature` x86/mm: 当 PCID 被禁用时关闭 broadcast TLB flush，优化无 PCID 场景下的 TLB 性能 [↗](https://lkml.org/lkml/2026/5/20/2039)\n- `feature` PCI/rzg3s: 为 RZ/V2H(P) SoC 添加 PCIe 主机控制器支持，完善瑞萨 SoC 生态系统 [↗](https://lkml.org/lkml/2026/5/20/1958)\n- `feature` KVM/riscv: 修复 hugetlb G-stage 块映射的合规性检查问题，确保大页映射正确处理 [↗](https://lkml.org/lkml/2026/5/20/1709)\n- `feature` KVM/s390: 实现 KVM_PRE_FAULT_MEMORY ioctl，允许用户空间预热虚拟机内存以提升启动速度 [↗](https://lkml.org/lkml/2026/5/20/1794)\n- `feature` arm64/dts/s32: 为 S32G2/G3 平台添加 USB PHY 节点和 OTG pinctrl 配置，完善 USB 支持 [↗](https://lkml.org/lkml/2026/5/20/1701)\n- `feature` iommu: 允许设备驱动使用独立的 PASID 空间，为多租户场景提供更强的隔离能力 [↗](https://lkml.org/lkml/2026/5/20/1751)\n- `feature` PCI/eswin: 修复 dw_pcie_host_init() 失败时的资源泄漏问题，增强驱动健壮性 [↗](https://lkml.org/lkml/2026/5/20/1579)\n- `feature` nvmem: 添加树莓派 OTP nvmem 驱动，支持读取板载 OTP 内存数据用于硬件验证 [↗](https://lkml.org/lkml/2026/5/20/1571)\n- `feature` arm64/dts/qcom: 在 Glymur SoC 上启用 ADSP 和 CDSP，提供完整的音频与计算 DSP 支持 [↗](https://lkml.org/lkml/2026/5/20/1540)\n- `feature` arm64/dts/renesas: 为 r9a07g044 的串口添加 DMA 属性配置，提升 UART 数据传输效率 [↗](https://lkml.org/lkml/2026/5/20/1360)\n- `feature` riscv/dts/spacemit: 为 k1-musepi-pro 开发板添加 SD 卡支持，扩展存储能力 [↗](https://lkml.org/lkml/2026/5/20/1332)\n- `feature` arm64/dts/ti: 为 J721S2 EVM 启用音频支持，完善德仪平台音频生态 [↗](https://lkml.org/lkml/2026/5/20/1158)\n- `feature` USB/serial/option: 为 RGMII 接口添加缺失的 RSVD(5) 标志，确保设备正确初始化 [↗](https://lkml.org/lkml/2026/5/20/1160)\n- `feature` riscv/dts/spacemit: 设置 OrangePi RV2 控制台波特率，改善串口通信配置 [↗](https://lkml.org/lkml/2026/5/20/1010)\n- `feature` USB/serial/mct_u232: 修复缺失的中断-IN 传输处理逻辑，解决数据传输可靠性问题 [↗](https://lkml.org/lkml/2026/5/20/930)\n- `feature` riscv/dts/spacemit: 为 OrangePi R2S 启用 PMIC，完善电源管理配置 [↗](https://lkml.org/lkml/2026/5/20/876)\n- `feature` arm64/dts/qcom: 为 qcs6490-rb3gen2 添加 rmtfs 节点，支持远程文件系统访问 [↗](https://lkml.org/lkml/2026/5/20/850)\n- `feature` USB/early/xhci-dbc: 确保早期调试控制器的内存大小分配正确，防止越界访问 [↗](https://lkml.org/lkml/2026/5/20/827)\n- `feature` USB/typec/ucsi: 添加 Cypress CYPD6129 UCSI 驱动支持，实现 USB-C 端口控制器的标准化管理 [↗](https://lkml.org/lkml/2026/5/20/818)\n- `feature` kdump: 优化崩溃转储机制以减小 vmcore 文件大小并缩短采集时间，提升系统恢复效率 [↗](https://lkml.org/lkml/2026/5/20/736)\n- `feature` powerpc/code-patching: 避免对零页面使用读写映射，防止安全隐患 [↗](https://lkml.org/lkml/2026/5/20/672)\n- `feature` PCI/imx6: 集成 pwrctrl API 并更新设备树配置，统一电源控制接口 [↗](https://lkml.org/lkml/2026/5/20/750)\n- `feature` USB/serial/digi_acceleport: 修复小缓冲区场景下的内存损坏问题，增强驱动安全性 [↗](https://lkml.org/lkml/2026/5/20/482)\n- `feature` s390/crypto: 添加 CRYPTO_AEAD 选择以启用 AES 认证加密支持，完善密码学子系统 [↗](https://lkml.org/lkml/2026/5/20/451)\n- `feature` arm64/dts/imx95: 修正 PCIe 出站地址空间配置，确保 IOMMU 翻译正确工作 [↗](https://lkml.org/lkml/2026/5/20/427)\n- `feature` Rust/powerpc: 为 powerpc 架构添加 Rust 语言支持，扩展内核开发选项 [↗](https://lkml.org/lkml/2026/5/20/359)\n- `feature` arm64/mm: 重命名 ptdesc_t 为更符合规范的名称，提升代码可读性 [↗](https://lkml.org/lkml/2026/5/20/321)\n- `feature` usb/dwc2: 修复调试代码中的 use-after-free 问题，消除潜在崩溃 [↗](https://lkml.org/lkml/2026/5/20/285)\n- `feature` arm64/dts/qcom: 为 glymur 平台添加 coresight 节点，支持性能追踪与调试 [↗](https://lkml.org/lkml/2026/5/20/106)\n- `feature` riscv/kexec_file: 将段放置约束到直接映射区域，确保 kexec 文件引导的内存布局正确 [↗](https://lkml.org/lkml/2026/5/20/13)\n- `feature` riscv: 无条件选择 ARCH_KEEP_MEMBLOCK 以保留 memblock 区域信息，支持内核诊断功能 [↗](https://lkml.org/lkml/2026/5/20/11)\n- `bugfix` soc: 修复多个 SoC 平台设备树中的兼容性问题，确保硬件正确识别 [↗](https://lkml.org/lkml/2026/5/20/2617)\n- `bugfix` PCI/sysfs: 在 kfree 后将 res_attr slot 置空防止 use-after-free，增强 sysfs 接口安全性 [↗](https://lkml.org/lkml/2026/5/20/2612)\n- `bugfix` x86/pvh: 修复 PVH 虚拟机与 KASAN 组合下的不可启动问题，解决早期引导崩溃 [↗](https://lkml.org/lkml/2026/5/20/2614)\n- `bugfix` arm_ffa/KVM: 修正 FF-A 内存描述符偏移计算，确保安全世界通信正确 [↗](https://lkml.org/lkml/2026/5/20/2315)\n- `bugfix` dmaengine/idxd: 修复初始化错误路径中的资源泄漏与状态不一致问题 [↗](https://lkml.org/lkml/2026/5/20/1608)\n- `bugfix` USB/serial/mct_u232: 修复小缓冲区场景下的内存损坏问题，防止数据泄露 [↗](https://lkml.org/lkml/2026/5/20/923)\n- `bugfix` powerpc/fadump: 修复 MIN_RMA 大小检查中的整数溢出漏洞，防止配置错误 [↗](https://lkml.org/lkml/2026/5/20/278)\n- `bugfix` cpu/hotplug: 修复 cpuhp_smt_enable() 中的空指针解引用警告，确保 CPU 热插拔稳定 [↗](https://lkml.org/lkml/2026/5/20/136)\n- `other` 其他改动多为小修正、清理或配置更新，整体风险较低，详情见：[↗](https://lkml.org/lkml/2026/5/20/2641) [↗](https://lkml.org/lkml/2026/5/20/2636) [↗](https://lkml.org/lkml/2026/5/20/2376) [↗](https://lkml.org/lkml/2026/5/20/1514) [↗](https://lkml.org/lkml/2026/5/20/793)\n\n## Power Management\n- `other` 其他改动多为小修正、清理或配置更新，整体风险较低，详情见：[↗](https://lkml.org/lkml/2026/5/20/194) [↗](https://lkml.org/lkml/2026/5/20/386) [↗](https://lkml.org/lkml/2026/5/20/1919) [↗](https://lkml.org/lkml/2026/5/20/697) [↗](https://lkml.org/lkml/2026/5/20/570) [↗](https://lkml.org/lkml/2026/5/20/2006) [↗](https://lkml.org/lkml/2026/5/20/729)\n\n## Clocks & Timers\n- `other` 其他改动多为小修正、清理或配置更新，整体风险较低，详情见：[↗](https://lkml.org/lkml/2026/5/20/2105) [↗](https://lkml.org/lkml/2026/5/20/1694) [↗](https://lkml.org/lkml/2026/5/20/802) [↗](https://lkml.org/lkml/2026/5/20/775) [↗](https://lkml.org/lkml/2026/5/20/43)\n\n## Core Kernel\n- `other` 其他改动多为小修正、清理或配置更新，整体风险较低，详情见：[↗](https://lkml.org/lkml/2026/5/20/936) [↗](https://lkml.org/lkml/2026/5/20/2004) [↗](https://lkml.org/lkml/2026/5/20/1934) [↗](https://lkml.org/lkml/2026/5/20/2277) [↗](https://lkml.org/lkml/2026/5/20/555) [↗](https://lkml.org/lkml/2026/5/20/198) [↗](https://lkml.org/lkml/2026/5/20/183) [↗](https://lkml.org/lkml/2026/5/20/569) [↗](https://lkml.org/lkml/2026/5/20/322)\n\n## IO_uring\n- `other` 其他改动多为小修正、清理或配置更新，整体风险较低，详情见：[↗](https://lkml.org/lkml/2026/5/20/2111) [↗](https://lkml.org/lkml/2026/5/20/318)\n\n## Virtualization\n- `other` 其他改动多为小修正、清理或配置更新，整体风险较低，详情见：[↗](https://lkml.org/lkml/2026/5/20/1620) [↗](https://lkml.org/lkml/2026/5/20/1013) [↗](https://lkml.org/lkml/2026/5/20/464) [↗](https://lkml.org/lkml/2026/5/20/422)\n\n## Drivers\n- `perf` `feature` drm/msm新增PERFCNTR_CONFIG ioctl，允许用户空间配置性能计数器，为GPU性能调优和调试提供底层接口 [↗](https://lkml.org/lkml/2026/5/20/1989)\n- `perf` `feature` HID驱动新增CP2112 SMBus转USB芯片的固件支持，增强USB-HID设备在Linux下的兼容性 [↗](https://lkml.org/lkml/2026/5/20/1973)\n- `perf` `feature` drm/scheduler新增并发任务提交测试套件，验证GPU调度器在高负载下的稳定性 [↗](https://lkml.org/lkml/2026/5/20/812)\n- `feature` DRM HDMI QP驱动添加HDMI 2.0支持，实现更高的带宽和分辨率，需与显示链路配合升级 [↗](https://lkml.org/lkml/2026/5/20/2416)\n- `feature` gpiolib废弃遗留接口，推动新API的采用，提升GPIO子系统的可维护性 [↗](https://lkml.org/lkml/2026/5/20/2121)\n- `feature` iio新增Open Sensor Fusion UART驱动，为惯性传感器融合提供标准化接口 [↗](https://lkml.org/lkml/2026/5/20/443)\n- `feature` max98090音频编解码器切换到标准set_jack回调，简化与上层ALSA的集成 [↗](https://lkml.org/lkml/2026/5/20/1844)\n- `feature` panthor GEM支持向用户空间报告对象换出状态，便于内存管理调试 [↗](https://lkml.org/lkml/2026/5/20/1325)\n- `feature` ADM1266 PMBus器件增加清空黑盒记录和上电功能，完善硬件监控能力 [↗](https://lkml.org/lkml/2026/5/20/2644)\n- `feature` ADM1266序列化固件版本debugfs输出，避免并发访问时的竞态条件 [↗](https://lkml.org/lkml/2026/5/20/2052)\n- `feature` MSI Claw新增HID配置驱动，为特定游戏外设提供驱动支持 [↗](https://lkml.org/lkml/2026/5/20/98)\n- `feature` is31fl32xx LED驱动新增powerdown引脚控制，完善电源管理 [↗](https://lkml.org/lkml/2026/5/20/1481)\n- `feature` iio加速度计bmc150使用guard(mutex)简化代码，提升可读性 [↗](https://lkml.org/lkml/2026/5/20/916)\n- `feature` mpu3050陀螺仪使用devm_iio_trigger_register简化资源管理 [↗](https://lkml.org/lkml/2026/5/20/150)\n- `feature` mpu3050陀螺仪使用devm_iio_trigger_register统一触发器注册模式 [↗](https://lkml.org/lkml/2026/5/20/1001)\n- `feature` qcom-spmi-iadc平衡enable_irq_wake调用，防止唤醒源泄露 [↗](https://lkml.org/lkml/2026/5/21/11)\n- `feature` bno055 IMU修复dev_err字符串未以换行符结尾的问题，改善日志格式 [↗](https://lkml.org/lkml/2026/5/21/10)\n- `feature` al3010光照传感器重新读取两个ALS ADC寄存器，确保数据完整性 [↗](https://lkml.org/lkml/2026/5/20/2053)\n- `feature` ad5686 DAC更新of_match_table以匹配设备树节点 [↗](https://lkml.org/lkml/2026/5/20/2341)\n- `feature` sdhci在resume时添加信号电压切换，确保热插拔后通信正常 [↗](https://lkml.org/lkml/2026/5/20/1480)\n- `feature` DRM连接器debugfs增加SCDC信息显示，便于HDMI调试 [↗](https://lkml.org/lkml/2026/5/20/1381)\n- `feature` is31fl32xx LED驱动v6版本完善powerdown gpio支持 [↗](https://lkml.org/lkml/2026/5/20/1367)\n- `feature` max98090切到标准set_jack回调统一接口 [↗](https://lkml.org/lkml/2026/5/20/1366)\n- `feature` i2c riic驱动修复和清理，提升代码质量 [↗](https://lkml.org/lkml/2026/5/20/1323)\n- `feature` GPIO共享代理在释放时撤销投票，防止资源泄漏 [↗](https://lkml.org/lkml/2026/5/20/1293)\n- `feature` GPIO聚合器在停用时移除软件节点，修复潜在内存问题 [↗](https://lkml.org/lkml/2026/5/20/1220)\n- `feature` pca953x在resume时正确传播regulator_enable()错误，确保电源管理一致性 [↗](https://lkml.org/lkml/2026/5/20/999)\n- `feature` i2c imx修复运行时时钟和引脚状态不一致问题，提升稳定性 [↗](https://lkml.org/lkml/2026/5/20/979)\n- `feature` i2c imx标记适配器在硬件断电时的状态，便于系统管理 [↗](https://lkml.org/lkml/2026/5/20/902)\n- `feature` i2c imx-lpi2c改用devm函数修复资源泄漏问题 [↗](https://lkml.org/lkml/2026/5/20/811)\n- `feature` tc358768桥接芯片在PLL设置后添加延迟，确保时序正确 [↗](https://lkml.org/lkml/2026/5/20/769)\n- `feature` dw-hdmi-qp根据N值计算音频CTS时钟，改善音频同步 [↗](https://lkml.org/lkml/2026/5/20/789)\n- `feature` GPIO聚合器修复潜在use-after-free问题，提升安全性 [↗](https://lkml.org/lkml/2026/5/20/765)\n- `feature` GPIO核心新增kunit单元测试，完善测试覆盖 [↗](https://lkml.org/lkml/2026/5/20/590)\n- `feature` GPIO cdev检查uAPI v2配置属性正确性，防止错误配置 [↗](https://lkml.org/lkml/2026/5/20/459)\n- `feature` i2c qcom-geni使用pm_runtime强制函数简化挂起恢复逻辑 [↗](https://lkml.org/lkml/2026/5/20/411)\n- `feature` SOC UBWC配置数据库重构，优化存储带宽压缩配置 [↗](https://lkml.org/lkml/2026/5/20/1612)\n- `feature` HDMI TMDS字符率常量添加到公共头文件，统一驱动实现 [↗](https://lkml.org/lkml/2026/5/20/1626)\n- `feature` DS1307 RTC新增Epson RX8901CE芯片支持，扩展兼容设备 [↗](https://lkml.org/lkml/2026/5/20/1655)\n- `feature` i2c mt7621改进Airoha设备支持，完善驱动兼容性 [↗](https://lkml.org/lkml/2026/5/20/55)\n- `feature` i2c mux-mule移除devm_add_action失败时的错误打印，减少噪音日志 [↗](https://lkml.org/lkml/2026/5/20/1692)\n- `feature` SOF Intel hda修复可能导致空指针解引用的问题 [↗](https://lkml.org/lkml/2026/5/20/172)\n- `bugfix` iio lmp91000电位计驱动修复probe时的空指针解引用，防止崩溃 [↗](https://lkml.org/lkml/2026/5/20/2455)\n- `bugfix` regmap-i2c修复smbus_word_write时的稀疏警告，确保代码通过静态分析 [↗](https://lkml.org/lkml/2026/5/20/1768)\n- `bugfix` spi fsl-lpspi修复DMA终止问题，防止数据传输不完整 [↗](https://lkml.org/lkml/2026/5/20/840)\n- `bugfix` i2c imx-lpi2c在probe阶段重置控制器，确保从已知状态启动 [↗](https://lkml.org/lkml/2026/5/20/725)\n- `bugfix` ALSA caiaq在设备release时持有USB设备引用，防止use-after-free [↗](https://lkml.org/lkml/2026/5/20/473)\n- `bugfix` SOF Intel hda修复可能导致空指针解引用的并发问题 [↗](https://lkml.org/lkml/2026/5/20/175)\n- `bugfix` virtio_console修复hvc put_chars与virtio写操作之间的竞态条件 [↗](https://lkml.org/lkml/2026/5/20/7)\n- `other` 其他改动多为小修正、清理或配置更新，整体风险较低，详情见：[↗](https://lkml.org/lkml/2026/5/20/723)\n\n## Other\n该补丁涉及108个未匹配到固定子系统规则的变更，主要分布在drivers/media、drivers/dpll、drivers/soc等驱动目录及Documentation目录下的devicetree、bindings、admin-guide等文档目录中。\nUnmatched by fixed subsystem rules: 108 items. Consider extending directory rules to improve classification.\n标签统计：`feature` 67 / `bugfix` 18 / `other` 23 / `perf` 3。",
  "stats": {
    "total": 349,
    "feature": 230,
    "bugfix": 70,
    "other": 49
  }
}