{
  "date": "2026-05-24",
  "sourceName": "Mailing List",
  "sourceType": "lkml",
  "generatedAt": "2026-05-23T20:02:19.419Z",
  "summary": "# 今日社区动态（MiniMax-M2.7 | 2026-05-23 ~ 2026-05-24）\n\n- 🧠 [Memory](#subsystem-Memory)：多为小修正、清理与配置更新，整体风险低\n- 🧭 [Scheduling](#subsystem-Scheduling)：主要是小修正和清理，维护工作量低\n- 🌐 [Networking](#subsystem-Networking)：涉及大量链接的小修正与清理工作，无显著新功能\n- 📈 [Observability](#subsystem-Observability)：KVM selftests 新增 PowerPC 框架与 Hyper-V 特性验证，BPF 增强安全检查与溢出防护，resctrl 放宽 CAT 测试限制\n- 🗂 [Filesystem & Storage](#subsystem-Filesystem%20%26%20Storage)：NVMe 添加 APST 延迟状态日志便于调试，UFS 支持静态 TX 均衡优化信号完整性，Btrfs 7.1-rc5 修复多模块稳定性问题，NTFS/ksmbd/nfsd 等修复关键路径 bug\n- 🏗 [Architecture](#subsystem-Architecture)：多架构支持的小修正与清理，维护工作为主\n- 🔋 [Power Management](#subsystem-Power%20Management)：小修正与清理，维持现有功能\n- ⚙ [Core Kernel](#subsystem-Core%20Kernel)：核心组件的小修正与清理\n- 🧩 [Virtualization](#subsystem-Virtualization)：虚拟化相关的小修正\n- 🧰 [Drivers](#subsystem-Drivers)：DRM 全面添加 YCBCR444/YCBCR420 颜色格式与 HDMI 辅助函数提升显示兼容性，iio 多驱动改用 RAII 简化并发控制，修复 HID 日志级别与 amdkfd 整数溢出等安全问题\n\n## Memory\n- `other` 其他改动多为小修正、清理或配置更新，整体风险较低，详情见：[↗](https://lkml.org/lkml/2026/5/23/603) [↗](https://lkml.org/lkml/2026/5/23/548) [↗](https://lkml.org/lkml/2026/5/23/127)\n\n## Scheduling\n- `other` 其他改动多为小修正、清理或配置更新，整体风险较低，详情见：[↗](https://lkml.org/lkml/2026/5/23/98)\n\n## Networking\n- `other` 其他改动多为小修正、清理或配置更新，整体风险较低，详情见：[↗](https://lkml.org/lkml/2026/5/23/606) [↗](https://lkml.org/lkml/2026/5/23/473) [↗](https://lkml.org/lkml/2026/5/23/365) [↗](https://lkml.org/lkml/2026/5/23/233) [↗](https://lkml.org/lkml/2026/5/23/236) [↗](https://lkml.org/lkml/2026/5/23/202) [↗](https://lkml.org/lkml/2026/5/23/461) [↗](https://lkml.org/lkml/2026/5/23/455) [↗](https://lkml.org/lkml/2026/5/23/451) [↗](https://lkml.org/lkml/2026/5/23/448) [↗](https://lkml.org/lkml/2026/5/23/386) [↗](https://lkml.org/lkml/2026/5/23/384) [↗](https://lkml.org/lkml/2026/5/23/323) [↗](https://lkml.org/lkml/2026/5/23/315) [↗](https://lkml.org/lkml/2026/5/23/184) [↗](https://lkml.org/lkml/2026/5/23/65) [↗](https://lkml.org/lkml/2026/5/23/310) [↗](https://lkml.org/lkml/2026/5/23/219) [↗](https://lkml.org/lkml/2026/5/23/217) [↗](https://lkml.org/lkml/2026/5/23/131) [↗](https://lkml.org/lkml/2026/5/23/469)\n\n## Observability\n- `feature` `KVM selftests: 在hyperv_features测试中验证HV_X64特性寄存器的写入行为` - 添加对Hyper-V特定特性寄存器的写入测试，确保KVM对Hyper-V扩展功能的正确支持，增强测试覆盖率并验证虚拟化功能的正确实现 [↗](https://lkml.org/lkml/2026/5/23/335)\n- `feature` `KVM selftests: 引入powerpc架构支持框架` - 为KVM自测工具添加完整的PowerPC支持，包括处理器抽象、hypercall接口、架构特定工具函数等基础设施，使得在不同架构上验证KVM功能成为可能 [↗](https://lkml.org/lkml/2026/5/23/327)\n- `feature` `selftests/resctrl: 在非独占缓存资源下允许CAT测试执行` - 放宽CAT(缓存分配技术)测试的先决条件，使其在共享缓存资源环境下也能运行，扩展了测试的适用范围，让资源受限环境也能进行缓存功能验证 [↗](https://lkml.org/lkml/2026/5/23/298)\n- `feature` `bpf: 为BPF_LSM_CGROUP添加安全检查的返回值验证逻辑` - 在LSM挂钩点增强对返回值的检查，确保安全模块能正确处理BPF程序返回的决策结果，防止因返回值处理不当导致的安全策略绕过问题 [↗](https://lkml.org/lkml/2026/5/23/231)\n- `feature` `bpf: 在btf_find_field_one()中增加数组元素数量溢出检查` - 添加对BTF类型描述中数组元素数量的边界验证，防止因恶意或错误元数据导致的整数溢出问题，提升BPF类型系统的安全性和健壮性 [↗](https://lkml.org/lkml/2026/5/23/175)\n- `feature` `netlink: 添加OVS packet家族的YNL规范定义和单播消息支持` - 通过YNL(Netlink Yadiana Library)规范方式定义Open vSwitch数据包接口，并实现单播通信支持，为用户空间与内核的OVS通信提供更规范、更易维护的接口定义 [↗](https://lkml.org/lkml/2026/5/23/5)\n- `other` 其他改动多为小修正、清理或配置更新，整体风险较低，详情见：[↗](https://lkml.org/lkml/2026/5/24/5)\n\n## Filesystem & Storage\n- `perf` `feature` 为 NVMe 驱动添加 APST 延迟上限跳过状态的日志记录，便于性能调试和电源管理优化 [↗](https://lkml.org/lkml/2026/5/23/349)\n- `feature` Btrfs 7.1-rc5 版本的修复合入，涵盖 extent_map、file、inode、qgroup 等模块，提升文件系统稳定性 [↗](https://lkml.org/lkml/2026/5/23/464)\n- `feature` 为 UFS 核心添加静态 TX 均衡支持，优化存储设备的信号完整性和传输性能 [↗](https://lkml.org/lkml/2026/5/23/405)\n- `feature` 移除 ext2 文件系统中已弃用的 DAX 支持，清理过时代码并减轻维护负担 [↗](https://lkml.org/lkml/2026/5/23/370)\n- `feature` NTFS 加强 EA 和索引元数据的验证，增强文件系统完整性检查和安全性 [↗](https://lkml.org/lkml/2026/5/23/88)\n- `feature` 为 SCSI 错误处理添加 EH 运行时 PM 的 get/put 配对机制，优化电源管理配对逻辑 [↗](https://lkml.org/lkml/2026/5/23/83)\n- `bugfix` 修复 eventpoll 中 clear_tfile_check_list() 的 use-after-free 问题，防止内存释放后被访问导致的崩溃 [↗](https://lkml.org/lkml/2026/5/23/223)\n- `bugfix` 修复 fcntl 中 send_sigio() 的 SOFTIRQ 不安全锁顺序问题，消除潜在的死锁风险 [↗](https://lkml.org/lkml/2026/5/23/179)\n- `bugfix` ksmbd 服务器修复，针对 smb2pdu、smbacl、vfs_cache 模块，提升 SMB 服务的稳定性和正确性 [↗](https://lkml.org/lkml/2026/5/23/445)\n- `bugfix` 修复 tmpfs/ramfs 使 memfd_create() 能在 nommu 架构上工作，扩展了在无 MMU 设备上的支持 [↗](https://lkml.org/lkml/2026/5/23/385)\n- `bugfix` nfsd 目录委托的后续修复，增强 NFS 分布式文件系统的委托处理正确性 [↗](https://lkml.org/lkml/2026/5/23/497)\n- `bugfix` lockd 修复确保 nlm_inspect_file 锁释放时正确固定下一个文件，维持锁管理状态一致性 [↗](https://lkml.org/lkml/2026/5/23/373)\n- `other` 其他改动多为小修正、清理或配置更新，整体风险较低，详情见：[↗](https://lkml.org/lkml/2026/5/23/383) [↗](https://lkml.org/lkml/2026/5/23/559)\n\n## Architecture\n- `other` 其他改动多为小修正、清理或配置更新，整体风险较低，详情见：[↗](https://lkml.org/lkml/2026/5/23/592) [↗](https://lkml.org/lkml/2026/5/23/552) [↗](https://lkml.org/lkml/2026/5/23/492) [↗](https://lkml.org/lkml/2026/5/23/423) [↗](https://lkml.org/lkml/2026/5/23/406) [↗](https://lkml.org/lkml/2026/5/23/235) [↗](https://lkml.org/lkml/2026/5/23/531) [↗](https://lkml.org/lkml/2026/5/23/526) [↗](https://lkml.org/lkml/2026/5/23/293) [↗](https://lkml.org/lkml/2026/5/23/275) [↗](https://lkml.org/lkml/2026/5/23/210) [↗](https://lkml.org/lkml/2026/5/23/197) [↗](https://lkml.org/lkml/2026/5/23/166) [↗](https://lkml.org/lkml/2026/5/23/140) [↗](https://lkml.org/lkml/2026/5/23/96) [↗](https://lkml.org/lkml/2026/5/23/72) [↗](https://lkml.org/lkml/2026/5/23/27) [↗](https://lkml.org/lkml/2026/5/23/22)\n\n## Power Management\n- `other` 其他改动多为小修正、清理或配置更新，整体风险较低，详情见：[↗](https://lkml.org/lkml/2026/5/23/206) [↗](https://lkml.org/lkml/2026/5/23/117)\n\n## Core Kernel\n- `other` 其他改动多为小修正、清理或配置更新，整体风险较低，详情见：[↗](https://lkml.org/lkml/2026/5/23/588) [↗](https://lkml.org/lkml/2026/5/23/144)\n\n## Virtualization\n- `other` 其他改动多为小修正、清理或配置更新，整体风险较低，详情见：[↗](https://lkml.org/lkml/2026/5/23/394) [↗](https://lkml.org/lkml/2026/5/23/101)\n\n## Drivers\n- `perf` `feature` drm/i915/dp: 添加YCBCR444颜色格式处理以支持HDMI色彩空间转换，提升显示兼容性 [↗](https://lkml.org/lkml/2026/5/23/613)\n- `perf` `feature` drm/amdgpu: 实现\"颜色格式\"DRM属性并支持YCBCR420子采样，完善HDMI色彩空间管理 [↗](https://lkml.org/lkml/2026/5/23/610)\n- `perf` `feature` drm/display: hdmi-state-helper实现色彩格式协商时的子采样回退机制，优化连接兼容性 [↗](https://lkml.org/lkml/2026/5/23/609)\n- `perf` `feature` drm/display: hdmi-state-helper基于色彩格式采取相应动作，完善HDMI状态处理 [↗](https://lkml.org/lkml/2026/5/23/608)\n- `feature` drm/amd/display: 移除不必要的SIGNAL_TYPE相关代码，简化显示驱动逻辑 [↗](https://lkml.org/lkml/2026/5/23/612)\n- `feature` drm/i915: 使用'depends on'替代'includes'确保DEBUG_OBJECTS配置可见性，修复构建依赖 [↗](https://lkml.org/lkml/2026/5/23/490)\n- `feature` drm/hyperv: 加强主机消息解析的安全性，防止恶意输入 [↗](https://lkml.org/lkml/2026/5/23/415)\n- `feature` drm/bridge: ite-it66121切换至HDMI辅助函数并实现色彩格式属性，现代化桥接驱动 [↗](https://lkml.org/lkml/2026/5/23/305)\n- `feature` drm: 添加msm dp-controller和qcom display绑定及amdxdna加速驱动支持 [↗](https://lkml.org/lkml/2026/5/23/46)\n- `feature` iio: scd30: 用RAII模式替代手动锁管理，简化并发控制代码 [↗](https://lkml.org/lkml/2026/5/23/581)\n- `feature` iio: sps30: 用RAII模式替代手动锁管理，现代化驱动代码 [↗](https://lkml.org/lkml/2026/5/23/580)\n- `feature` iio: al3010: 重新读取ALS ADC寄存器以提高精度，修复传感器读取问题 [↗](https://lkml.org/lkml/2026/5/23/340)\n- `feature` iio: qcom-spmi-iadc: 平衡enable_irq_wake()调用，确保电源管理正确性 [↗](https://lkml.org/lkml/2026/5/23/403)\n- `feature` PM: sleep: 在device_pm_sleep_init()中使用complete()，完善电源管理初始化 [↗](https://lkml.org/lkml/2026/5/23/71)\n- `feature` mtd: spi-nor: 添加ISSI SPI-NOR设备JEDEC ID表项，扩展新设备支持 [↗](https://lkml.org/lkml/2026/5/23/60)\n- `bugfix` drm/amdkfd: 修复get_queue_ids()中整数溢出问题，防止潜在安全风险 [↗](https://lkml.org/lkml/2026/5/23/450)\n- `bugfix` HID: wacom: 修复wacom_intuos_pad()中NULL指针解引用，提升稳定性 [↗](https://lkml.org/lkml/2026/5/24/1)\n- `bugfix` HID: core: 将数据不足警告降级为调试级别，减少不必要的日志输出 [↗](https://lkml.org/lkml/2026/5/23/312)\n- `bugfix` HID: core: 将数据长度警告降级为调试级别，优化日志级别 [↗](https://lkml.org/lkml/2026/5/23/304)\n- `bugfix` input: atmel_mxt_ts: 修复异步配置释放后使用问题，防止内存错误 [↗](https://lkml.org/lkml/2026/5/23/478)\n- `bugfix` driver core: 修复平台驱动和固件接口相关问题，完善驱动核心 [↗](https://lkml.org/lkml/2026/5/23/387)\n- `bugfix` hwmon: 合并hwmon修复用于v7.1-rc5，改进硬件监控支持 [↗](https://lkml.org/lkml/2026/5/23/530)\n- `other` 其他改动多为小修正、清理或配置更新，整体风险较低，详情见：[↗](https://lkml.org/lkml/2026/5/23/46) [↗](https://lkml.org/lkml/2026/5/23/102)\n\n## Other\n本次共有41个补丁，主要涉及drivers/staging、drivers/counter、drivers/pinctrl、rust/kernel、drivers/accel等子系统，涵盖内核驱动和Rust语言的改动。\nUnmatched by fixed subsystem rules: 41 items. Consider extending directory rules to improve classification.\n标签统计：`feature` 22 / `bugfix` 9 / `other` 10 / `perf` 4。",
  "stats": {
    "total": 135,
    "feature": 87,
    "bugfix": 29,
    "other": 19
  }
}